odoo/addons/stock_picking_report_external_note/README.rst
odoo/addons/stock_picking_report_external_note/__init__.py
odoo/addons/stock_picking_report_external_note/__manifest__.py
odoo/addons/stock_picking_report_external_note/i18n/es.po
odoo/addons/stock_picking_report_external_note/i18n/it.po
odoo/addons/stock_picking_report_external_note/i18n/stock_picking_report_external_note.pot
odoo/addons/stock_picking_report_external_note/models/__init__.py
odoo/addons/stock_picking_report_external_note/models/stock_picking.py
odoo/addons/stock_picking_report_external_note/readme/CONTRIBUTORS.md
odoo/addons/stock_picking_report_external_note/readme/DESCRIPTION.md
odoo/addons/stock_picking_report_external_note/readme/USAGE.md
odoo/addons/stock_picking_report_external_note/report/report_deliveryslip.xml
odoo/addons/stock_picking_report_external_note/static/description/icon.png
odoo/addons/stock_picking_report_external_note/static/description/icon.svg
odoo/addons/stock_picking_report_external_note/static/description/index.html
odoo/addons/stock_picking_report_external_note/views/stock_picking_views.xml
odoo_addon_stock_picking_report_external_note-19.0.1.0.0.2.dist-info/METADATA
odoo_addon_stock_picking_report_external_note-19.0.1.0.0.2.dist-info/WHEEL
odoo_addon_stock_picking_report_external_note-19.0.1.0.0.2.dist-info/top_level.txt
odoo_addon_stock_picking_report_external_note-19.0.1.0.0.2.dist-info/RECORD
