Metadata-Version: 2.1
Name: odoo-addon-stock_picking_report_external_note
Version: 19.0.1.0.0.2
Requires-Dist: odoo==19.0.*
Summary: Adds a note in Stock Picking shown on external reports like Delivery Slip
Home-page: https://github.com/OCA/stock-logistics-reporting
License: AGPL-3
Author: Moduon, Odoo Community Association (OCA)
Author-email: support@odoo-community.org
Classifier: Programming Language :: Python
Classifier: Framework :: Odoo
Classifier: Framework :: Odoo :: 19.0
Classifier: License :: OSI Approved :: GNU Affero General Public License v3
Classifier: Development Status :: 4 - Beta
